django_zibanu/__init__.py
django_zibanu/apps.py
django_zibanu/utils.py
django_zibanu/db/__init__.py
django_zibanu/db/models.py
django_zibanu/enums/__init__.py
django_zibanu/lib/__init__.py
django_zibanu/lib/messages/__init__.py
django_zibanu/lib/messages/error_messages.py
django_zibanu/rest_framework/__init__.py
django_zibanu/rest_framework/decorators.py
django_zibanu/rest_framework/exceptions.py
django_zibanu/rest_framework/fields.py
django_zibanu/rest_framework/handlers.py
django_zibanu/rest_framework/serializers.py
django_zibanu/rest_framework/viewsets.py
django_zibanu-1.0.0a13.dist-info/LICENSE
django_zibanu-1.0.0a13.dist-info/METADATA
django_zibanu-1.0.0a13.dist-info/WHEEL
django_zibanu-1.0.0a13.dist-info/top_level.txt
django_zibanu-1.0.0a13.dist-info/RECORD
