Metadata-Version: 2.1
Name: django-zibanu
Version: 1.0.0a13
Summary: Zibanu Django Library.
Author-email: Mario Cerón Charry <mario.ceron@mceron.com>
License: GNU GENERAL PUBLIC LICENSE
Keywords: django,zibanu,rest framework,rest
Classifier: License :: OSI Approved :: MIT License
Classifier: Programming Language :: Python :: 3.9
Classifier: Development Status :: 3 - Alpha
Classifier: Framework :: Django
Classifier: Framework :: Django :: 3.2
Classifier: Environment :: Web Environment
Classifier: Operating System :: OS Independent
Classifier: Topic :: Software Development :: Libraries :: Application Frameworks
Requires-Python: >=3.7
License-File: LICENSE
Requires-Dist: django (>=3.2)
Requires-Dist: django-rest-framework
Requires-Dist: djangorestframework-simplejwt
